{
    "AX": {
        "error": 5.935163150461806e-07, 
        "error_type": "SEM", 
        "filter_outliers_dict": {
            "filter_outliers": true, 
            "iterations": 1, 
            "std_devs": 2
        }, 
        "fit": "average", 
        "value": 1.5555210969999997e-06
    }, 
    "H1": {
        "error": 5.476562397865406e-07, 
        "error_type": "SEM", 
        "filter_outliers_dict": {
            "filter_outliers": true, 
            "iterations": 1, 
            "std_devs": 2
        }, 
        "fit": "average", 
        "value": 1.198574909e-06
    }, 
    "H2": {
        "error": 5.795943016427674e-07, 
        "error_type": "SEM", 
        "filter_outliers_dict": {
            "filter_outliers": true, 
            "iterations": 1, 
            "std_devs": 2
        }, 
        "fit": "average", 
        "value": 4.581180595e-07
    }, 
    "L1": {
        "error": 2.460729747673182e-07, 
        "error_type": "SEM", 
        "filter_outliers_dict": {
            "filter_outliers": true, 
            "iterations": 1, 
            "std_devs": 2
        }, 
        "fit": "average", 
        "value": 2.0109514000000002e-07
    }, 
    "L2": {
        "error": 0.12758439472669758, 
        "error_type": "SEM", 
        "filter_outliers_dict": {
            "filter_outliers": true, 
            "iterations": 1, 
            "std_devs": 2
        }, 
        "fit": "average", 
        "value": 1.0833333333333333
    }
}