{
    "AX": {
        "error": 5.566288273210653e-07, 
        "error_type": "SEM", 
        "filter_outliers_dict": {
            "filter_outliers": true, 
            "iterations": 1, 
            "std_devs": 2
        }, 
        "fit": "average", 
        "value": 1.2480763176666667e-06
    }, 
    "H1": {
        "error": 3.338256812962377e-07, 
        "error_type": "SEM", 
        "filter_outliers_dict": {
            "filter_outliers": true, 
            "iterations": 1, 
            "std_devs": 2
        }, 
        "fit": "average", 
        "value": 1.0209034651666667e-06
    }, 
    "H2": {
        "error": 4.701053416086469e-07, 
        "error_type": "SEM", 
        "filter_outliers_dict": {
            "filter_outliers": true, 
            "iterations": 1, 
            "std_devs": 2
        }, 
        "fit": "average", 
        "value": 1.1627271278666667e-06
    }, 
    "L1": {
        "error": 4.2379086625724785e-07, 
        "error_type": "SEM", 
        "filter_outliers_dict": {
            "filter_outliers": true, 
            "iterations": 1, 
            "std_devs": 2
        }, 
        "fit": "average", 
        "value": -1.1847095683333336e-07
    }, 
    "L2": {
        "error": 0.1492574211815874, 
        "error_type": "SEM", 
        "filter_outliers_dict": {
            "filter_outliers": true, 
            "iterations": 1, 
            "std_devs": 2
        }, 
        "fit": "average", 
        "value": 0.8833333333333333
    }
}