{
    "Ar36": {
        "error": 28.229530689258016,
        "error_type": "SEM",
        "filter_outliers_dict": {
            "filter_outliers": false,
            "iterations": 0,
            "std_devs": 0,
            "use_iqr_filtering": false,
            "use_standard_deviation_filtering": false
        },
        "fit": "Linear",
        "fn": 600,
        "include_baseline_error": false,
        "n": 600,
        "outlier_excluded": [],
        "reviewed": true,
        "user_excluded": [],
        "value": 114590.74743017272
    },
    "Ar37": {
        "error": 5.320354617623267e-06,
        "error_type": "SEM",
        "filter_outliers_dict": {
            "filter_outliers": false,
            "iterations": 0,
            "std_devs": 0,
            "use_iqr_filtering": false,
            "use_standard_deviation_filtering": false
        },
        "fit": "Average",
        "fn": 600,
        "include_baseline_error": false,
        "n": 600,
        "outlier_excluded": [],
        "reviewed": true,
        "user_excluded": [],
        "value": -0.020284191767374674
    },
    "Ar38": {
        "error": 1.1728421506209177e-05,
        "error_type": "SEM",
        "filter_outliers_dict": {
            "filter_outliers": false,
            "iterations": 0,
            "std_devs": 0,
            "use_iqr_filtering": false,
            "use_standard_deviation_filtering": false
        },
        "fit": "Linear",
        "fn": 600,
        "include_baseline_error": false,
        "n": 600,
        "outlier_excluded": [],
        "reviewed": true,
        "user_excluded": [],
        "value": -0.014617159854461402
    },
    "Ar39": {
        "error": 4.854683268225019e-06,
        "error_type": "SEM",
        "filter_outliers_dict": {
            "filter_outliers": false,
            "iterations": 0,
            "std_devs": 0,
            "use_iqr_filtering": false,
            "use_standard_deviation_filtering": false
        },
        "fit": "Average",
        "fn": 600,
        "include_baseline_error": false,
        "n": 600,
        "outlier_excluded": [],
        "reviewed": true,
        "user_excluded": [],
        "value": -0.019077771902084352
    },
    "Ar40": {
        "error": 3.6339456093870285e-05,
        "error_type": "SEM",
        "filter_outliers_dict": {
            "filter_outliers": false,
            "iterations": 0,
            "std_devs": 0,
            "use_iqr_filtering": false,
            "use_standard_deviation_filtering": false
        },
        "fit": "Linear",
        "fn": 600,
        "include_baseline_error": false,
        "n": 600,
        "outlier_excluded": [],
        "reviewed": true,
        "user_excluded": [],
        "value": 0.672224789809298
    }
}