{
    "Ar36": {
        "error": 11.521548891207075,
        "error_type": "SEM",
        "filter_outliers_dict": {
            "filter_outliers": false,
            "iterations": 0,
            "std_devs": 0,
            "use_iqr_filtering": false,
            "use_standard_deviation_filtering": false
        },
        "fit": "Linear",
        "fn": 600,
        "include_baseline_error": false,
        "n": 600,
        "outlier_excluded": [],
        "reviewed": true,
        "user_excluded": [],
        "value": 18779.97001722223
    },
    "Ar37": {
        "error": 5.460543109871671e-06,
        "error_type": "SEM",
        "filter_outliers_dict": {
            "filter_outliers": false,
            "iterations": 0,
            "std_devs": 0,
            "use_iqr_filtering": false,
            "use_standard_deviation_filtering": false
        },
        "fit": "Average",
        "fn": 600,
        "include_baseline_error": false,
        "n": 600,
        "outlier_excluded": [],
        "reviewed": true,
        "user_excluded": [],
        "value": -0.019430708885192872
    },
    "Ar38": {
        "error": 1.1171641972939821e-05,
        "error_type": "SEM",
        "filter_outliers_dict": {
            "filter_outliers": false,
            "iterations": 0,
            "std_devs": 0,
            "use_iqr_filtering": false,
            "use_standard_deviation_filtering": false
        },
        "fit": "Linear",
        "fn": 600,
        "include_baseline_error": false,
        "n": 600,
        "outlier_excluded": [],
        "reviewed": true,
        "user_excluded": [],
        "value": -0.017301850808966027
    },
    "Ar39": {
        "error": 5.021046999277366e-06,
        "error_type": "SEM",
        "filter_outliers_dict": {
            "filter_outliers": false,
            "iterations": 0,
            "std_devs": 0,
            "use_iqr_filtering": false,
            "use_standard_deviation_filtering": false
        },
        "fit": "Average",
        "fn": 600,
        "include_baseline_error": false,
        "n": 600,
        "outlier_excluded": [],
        "reviewed": true,
        "user_excluded": [],
        "value": -0.01805444359779358
    },
    "Ar40": {
        "error": 6.948638041019902e-06,
        "error_type": "SEM",
        "filter_outliers_dict": {
            "filter_outliers": false,
            "iterations": 0,
            "std_devs": 0,
            "use_iqr_filtering": false,
            "use_standard_deviation_filtering": false
        },
        "fit": "Linear",
        "fn": 600,
        "include_baseline_error": false,
        "n": 600,
        "outlier_excluded": [],
        "reviewed": true,
        "user_excluded": [],
        "value": 0.11170810705187492
    }
}