{
    "Ar36": {
        "error": 0.8474933425937785,
        "error_type": "",
        "fit": "previous",
        "references": [
            {
                "exclude": false,
                "record_id": "ba-01-N-682"
            }
        ],
        "value": 60.32688210237336
    },
    "Ar36L1": {
        "error": 3.902412809926822e-07,
        "error_type": "",
        "fit": "previous",
        "references": [
            {
                "exclude": false,
                "record_id": "ba-01-N-682"
            }
        ],
        "value": 2.2242827727676505e-06
    },
    "Ar37": {
        "error": 2.9546420956686774e-07,
        "error_type": "",
        "fit": "previous",
        "references": [
            {
                "exclude": false,
                "record_id": "ba-01-N-682"
            }
        ],
        "value": 4.635693692691958e-06
    },
    "Ar38": {
        "error": 3.5135816286753283e-07,
        "error_type": "",
        "fit": "previous",
        "references": [
            {
                "exclude": false,
                "record_id": "ba-01-N-682"
            }
        ],
        "value": 1.2643008632828355e-06
    },
    "Ar39": {
        "error": 3.131465944478866e-07,
        "error_type": "",
        "fit": "previous",
        "references": [
            {
                "exclude": false,
                "record_id": "ba-01-N-682"
            }
        ],
        "value": 1.0482639224732201e-06
    },
    "Ar40": {
        "error": 1.553713910740127e-06,
        "error_type": "",
        "fit": "previous",
        "references": [
            {
                "exclude": false,
                "record_id": "ba-01-N-682"
            }
        ],
        "value": 3.0876292502362074e-05
    }
}