{
    "Ar36": {
        "error": 0.9120269996519006,
        "error_type": "",
        "fit": "previous",
        "references": [
            {
                "exclude": false,
                "record_id": ""
            }
        ],
        "value": 120.29194875061773
    },
    "Ar38": {
        "error": 5.871302460990152e-07,
        "error_type": "",
        "fit": "previous",
        "references": [
            {
                "exclude": false,
                "record_id": ""
            }
        ],
        "value": 1.7708102840931998e-06
    },
    "Ar40": {
        "error": 6.312980002452165e-07,
        "error_type": "",
        "fit": "previous",
        "references": [
            {
                "exclude": false,
                "record_id": ""
            }
        ],
        "value": 1.0940161713590104e-05
    }
}